appose/__init__.py
appose/environment.py
appose/paths.py
appose/python_worker.py
appose/service.py
appose/types.py
appose-0.6.0.dist-info/licenses/LICENSE.txt
appose-0.6.0.dist-info/METADATA
appose-0.6.0.dist-info/WHEEL
appose-0.6.0.dist-info/top_level.txt
appose-0.6.0.dist-info/RECORD
