Metadata-Version: 2.4
Name: appose
Version: 0.6.0
Summary: Appose: multi-language interprocess cooperation with shared memory.
Author: Appose developers
License-Expression: BSD-2-Clause
Project-URL: homepage, https://github.com/apposed/appose-python
Project-URL: documentation, https://github.com/apposed/appose-python/blob/main/README.md
Project-URL: source, https://github.com/apposed/appose-python
Project-URL: download, https://pypi.org/project/appose-python
Project-URL: tracker, https://github.com/apposed/appose/issues
Keywords: java,javascript,python,cross-language,interprocess
Classifier: Development Status :: 2 - Pre-Alpha
Classifier: Intended Audience :: Developers
Classifier: Intended Audience :: Education
Classifier: Intended Audience :: Science/Research
Classifier: Programming Language :: Python :: 3 :: Only
Classifier: Programming Language :: Python :: 3.10
Classifier: Programming Language :: Python :: 3.11
Classifier: Programming Language :: Python :: 3.12
Classifier: Operating System :: Microsoft :: Windows
Classifier: Operating System :: Unix
Classifier: Operating System :: MacOS
Classifier: Topic :: Scientific/Engineering
Classifier: Topic :: Software Development :: Libraries :: Java Libraries
Classifier: Topic :: Software Development :: Libraries :: Python Modules
Classifier: Topic :: Utilities
Requires-Python: >=3.10
License-File: LICENSE.txt
Provides-Extra: dev
Requires-Dist: autopep8; extra == "dev"
Requires-Dist: black; extra == "dev"
Requires-Dist: build; extra == "dev"
Requires-Dist: flake8; extra == "dev"
Requires-Dist: flake8-pyproject; extra == "dev"
Requires-Dist: flake8-typing-imports; extra == "dev"
Requires-Dist: isort; extra == "dev"
Requires-Dist: pytest; extra == "dev"
Requires-Dist: numpy; extra == "dev"
Requires-Dist: toml; extra == "dev"
Requires-Dist: validate-pyproject[all]; extra == "dev"
Dynamic: license-file
